sigtekx/__init__.py
sigtekx-0.0.2.dist-info/licenses/LICENSE
sigtekx-0.0.2.dist-info/METADATA
sigtekx-0.0.2.dist-info/WHEEL
sigtekx-0.0.2.dist-info/top_level.txt
sigtekx-0.0.2.dist-info/RECORD
