Metadata-Version: 2.4
Name: sigtekx
Version: 0.0.2
Summary: GPU-accelerated signal processing pipeline builder for real-time FFT analysis
Author-email: Kevin Rahsaz <rahsaz.kevin@gmail.com>
License-Expression: MIT
Project-URL: Homepage, https://github.com/SEAL-Embedded/ionosense-hpc-lib
Project-URL: Documentation, https://github.com/SEAL-Embedded/ionosense-hpc-lib
Project-URL: Repository, https://github.com/SEAL-Embedded/ionosense-hpc-lib
Project-URL: Bug Tracker, https://github.com/SEAL-Embedded/ionosense-hpc-lib/issues
Keywords: signal-processing,fft,cuda,gpu,real-time,stft,spectrogram
Classifier: Development Status :: 4 - Beta
Classifier: Intended Audience :: Science/Research
Classifier: Intended Audience :: Developers
Classifier: Programming Language :: Python :: 3
Classifier: Programming Language :: Python :: 3.11
Classifier: Programming Language :: Python :: 3.12
Classifier: Programming Language :: C++
Classifier: Topic :: Scientific/Engineering
Classifier: Topic :: Scientific/Engineering :: Physics
Classifier: Topic :: Software Development :: Libraries :: Python Modules
Classifier: Operating System :: Microsoft :: Windows
Classifier: Operating System :: POSIX :: Linux
Requires-Python: >=3.11
License-File: LICENSE
Dynamic: license-file
